giga_test/22.txt
giga_test/__init__.py
giga_test/utils/11.txt
giga_test/utils/__init__.py
giga_test/utils/file.py
giga_test/utils/zero0.json
giga_test-1.0.0.dist-info/licenses/LICENSE
giga_test-1.0.0.dist-info/METADATA
giga_test-1.0.0.dist-info/WHEEL
giga_test-1.0.0.dist-info/top_level.txt
giga_test-1.0.0.dist-info/RECORD
